odoo10_addon_storage_image_product_pos-10.0.1.0.1-py3.8-nspkg.pth
odoo/addons/storage_image_product_pos/README.rst
odoo/addons/storage_image_product_pos/__init__.py
odoo/addons/storage_image_product_pos/__manifest__.py
odoo/addons/storage_image_product_pos/i18n/storage_image_product_pos.pot
odoo/addons/storage_image_product_pos/static/description/icon.png
odoo/addons/storage_image_product_pos/static/src/js/pos_product.js
odoo/addons/storage_image_product_pos/views/pos_product.xml
odoo10_addon_storage_image_product_pos-10.0.1.0.1.dist-info/METADATA
odoo10_addon_storage_image_product_pos-10.0.1.0.1.dist-info/WHEEL
odoo10_addon_storage_image_product_pos-10.0.1.0.1.dist-info/namespace_packages.txt
odoo10_addon_storage_image_product_pos-10.0.1.0.1.dist-info/top_level.txt
odoo10_addon_storage_image_product_pos-10.0.1.0.1.dist-info/RECORD
